wedroid/__init__.py
wedroid/config_helper.py
wedroid/core.py
wedroid/fakedroid.py
wedroid/log_config.ini
wedroid/logkit.py
wedroid/matterping.py
wedroid/setting_loader.py
wedroid/termux.py
wedroid/time_utilities.py
wedroid/translations/announcements.json
wedroid/translations/weather.json
WeDroid-1.4.1.dist-info/LICENSE
WeDroid-1.4.1.dist-info/METADATA
WeDroid-1.4.1.dist-info/WHEEL
WeDroid-1.4.1.dist-info/entry_points.txt
WeDroid-1.4.1.dist-info/top_level.txt
WeDroid-1.4.1.dist-info/RECORD
