Metadata-Version: 2.1
Name: WeDroid
Version: 1.4.1
Summary: A weather announcement agent that summarises weather in realtime using OpenWeatherMaps; Features additional support for Android devices using Termux & Tasker.
Home-page: https://oddineers.co.uk/applications/wedroid
Author: Steven
Author-email: steven@oddineers.co.uk
Project-URL: Documentation, https://oddineers.co.uk/applications/wedroid#docs
Project-URL: Say Thanks!, https://oddineers.co.uk/applications/wedroid#donate
Project-URL: Source, https://gitlab.com/oddineers-public/wedroid
Project-URL: Tracker, https://gitlab.com/oddineers-public/wedroid/-/issues
Keywords: weather development,owm
Classifier: Development Status :: 5 - Production/Stable
Classifier: Programming Language :: Python :: 3
Classifier: Programming Language :: Python :: 3.9
Classifier: Operating System :: OS Independent
Classifier: License :: OSI Approved :: Apache Software License
Classifier: Intended Audience :: End Users/Desktop
Classifier: Intended Audience :: Developers
Classifier: Intended Audience :: Education
Classifier: Intended Audience :: Information Technology
Classifier: Intended Audience :: Science/Research
Classifier: Topic :: Internet
Classifier: Topic :: Utilities
License-File: LICENSE
Requires-Dist: certifi >=2024.7.4
Requires-Dist: chardet >=5.2.0
Requires-Dist: charset-normalizer >=3.3.2
Requires-Dist: geojson >=2.5.0
Requires-Dist: idna >=3.8
Requires-Dist: pyowm >=3.3.0
Requires-Dist: PySocks >=1.7.1
Requires-Dist: requests >=2.32.3
Requires-Dist: setuptools >=74.0.0
Requires-Dist: urllib3 >=2.2.2
